agentsui/__init__.py
agentsui-0.0.1.dist-info/licenses/LICENSE
agentsui-0.0.1.dist-info/METADATA
agentsui-0.0.1.dist-info/WHEEL
agentsui-0.0.1.dist-info/top_level.txt
agentsui-0.0.1.dist-info/RECORD
