Metadata-Version: 2.4
Name: agentsui
Version: 0.0.1
Summary: Redirect package - Install 'agentui' instead
Author-email: Emrah NAZIF <emrah@datamarkin.com>, Datamarkin <support@datamarkin.com>
License: MIT
Project-URL: Correct Package, https://pypi.org/project/agentui/
Project-URL: Homepage, https://pypi.org/project/agentui/
Keywords: redirect,agentui,typo
Classifier: Development Status :: 1 - Planning
Classifier: Intended Audience :: Developers
Classifier: License :: OSI Approved :: MIT License
Classifier: Programming Language :: Python :: 3
Classifier: Programming Language :: Python :: 3.9
Classifier: Programming Language :: Python :: 3.10
Classifier: Programming Language :: Python :: 3.11
Classifier: Programming Language :: Python :: 3.12
Requires-Python: >=3.9
License-File: LICENSE
Dynamic: license-file
